README.rst
setup.py
src/dbs/__init__.py
src/dbs.gameanalytics.egg-info/PKG-INFO
src/dbs.gameanalytics.egg-info/SOURCES.txt
src/dbs.gameanalytics.egg-info/dependency_links.txt
src/dbs.gameanalytics.egg-info/namespace_packages.txt
src/dbs.gameanalytics.egg-info/top_level.txt
src/dbs.gameanalytics.egg-info/zip-safe
src/dbs/gameanalytics/__init__.py
src/dbs/gameanalytics/conf.py
src/dbs/gameanalytics/log.py