Metadata-Version: 1.1
Name: dbs.gameanalytics
Version: 0.1.1
Summary: Http://GameAnalytics.com REST API implementation
Home-page: http://www.dreambitstudios.com
Author: Domantas Jackūnas
Author-email: devops@dreambitstudios.com
License: BSD
Keywords: utilities color log
Platform: UNKNOWN
Classifier: Topic :: Utilities
Classifier: Environment :: Console
Classifier: Development Status :: 3 - Alpha
Classifier: Intended Audience :: Developers
Classifier: License :: OSI Approved :: BSD License
Classifier: Natural Language :: English
Classifier: Operating System :: Unix
Classifier: Programming Language :: Python
